wavenet/__init__.py
wavenet/cell.py
wavenet/network.py
wavenet/test_cells.py
wavenet/test_network.py
wavenet-0.1.2.dist-info/METADATA
wavenet-0.1.2.dist-info/RECORD
wavenet-0.1.2.dist-info/WHEEL
wavenet-0.1.2.dist-info/top_level.txt
